aequitas/__init__.py
aequitas/core/__init__.py
aequitas/core/__main__.py
aequitas/core/algorithms/__init__.py
aequitas/core/algorithms/inprocessing/__init__.py
aequitas/core/algorithms/postprocessing/__init__.py
aequitas/core/algorithms/preprocessing/__init__.py
aequitas/core/datasets/__init__.py
aequitas/core/datasets/zoo.py
aequitas/core/imputation/__init__.py
aequitas/core/metrics/__init__.py
aequitas_core-2.1.1.dist-info/LICENSE
aequitas_core-2.1.1.dist-info/METADATA
aequitas_core-2.1.1.dist-info/WHEEL
aequitas_core-2.1.1.dist-info/top_level.txt
aequitas_core-2.1.1.dist-info/RECORD
