Metadata-Version: 2.1
Name: aequitas-core
Version: 2.1.1
Summary: Aequitas core library
Home-page: https://github.com/aequitas-aod/core-lib
Author: Giovanni Ciatto
Author-email: giovanni.ciatto@unibo.it
License: Apache 2.0 License
Project-URL: Bug Reports, https://github.com/aequitas-aod/core-lib/issues
Project-URL: Source, https://github.com/aequitas-aod/core-lib
Keywords: aeuitas,horizon2020,xai,bias
Platform: Independant
Classifier: Development Status :: 3 - Alpha
Classifier: Intended Audience :: Developers
Classifier: Topic :: Software Development :: Libraries
Classifier: Topic :: Scientific/Engineering :: Artificial Intelligence
Classifier: License :: OSI Approved :: Apache Software License
Classifier: Programming Language :: Python :: 3
Classifier: Programming Language :: Python :: 3 :: Only
Requires-Python: >=3.9.18
License-File: LICENSE
Requires-Dist: aif360>=0.6.1
Requires-Dist: pandas>=2.2.3
Requires-Dist: BlackBoxAuditing
Requires-Dist: aif360[adversarialdebiasing]
Requires-Dist: aif360[reductions]
Requires-Dist: aif360[infairness]
Requires-Dist: scikit-learn~=1.5.1
Requires-Dist: numpy~=1.26.4
Requires-Dist: setuptools~=75.1.0
Requires-Dist: tensorflow
